{
	"fileVersion": 1,
	"versions": {
		"arsd-official": "10.9.10",
		"automem": "0.6.9",
		"bindbc-freetype": "1.0.5",
		"bindbc-loader": "1.0.3",
		"bindbc-opengl": "1.0.5",
		"bindbc-sdl": "1.0.1",
		"botan": {"version":"a0c206639debc7e5726c02fc399267e6a33571a0","repository":"git+https://github.com/Dadoum/botan.git"},
		"botan-math": "1.0.4",
		"cachetools": "0.4.1",
		"dlangui": "0.10.4",
		"dsfml": "2.1.1",
		"dxml": "0.4.3",
		"glx-d": "1.1.0",
		"gtk_d": "1.0.3",
		"icontheme": "1.2.3",
		"inilike": "1.2.2",
		"isfreedesktop": "0.1.1",
		"memutils": "1.0.9",
		"plist": "~master",
		"plist-d": {"version":"6a67af9f2b6064065508bbb63eed1fab470ea3be","repository":"git+https://github.com/Dadoum/libplist-d.git"},
		"provision": {"version":"f4a3f768932debd79610e361dcb0877e3a8ff798","repository":"git+https://github.com/Dadoum/Provision.git"},
		"requests": "2.0.9",
		"slf4d": "2.1.1",
		"test_allocator": "0.3.4",
		"unit-threaded": "0.10.8",
		"x11": "1.0.21",
		"xdgpaths": "0.2.5"
	}
}
